headlinehunt/__init__.py
headlinehunt/config.py
headlinehunt/default_settings.toml
headlinehunt/main.py
headlinehunt/provider/__init__.py
headlinehunt/provider/alpha_vantage.py
headlinehunt/provider/finnhub.py
headlinehunt/provider/gnews.py
headlinehunt/provider/google_news.py
headlinehunt/provider/newsplease.py
headlinehunt/provider/provider.py
headlinehunt-0.1.12.dist-info/LICENSE
headlinehunt-0.1.12.dist-info/METADATA
headlinehunt-0.1.12.dist-info/WHEEL
headlinehunt-0.1.12.dist-info/RECORD
