Metadata-Version: 2.1
Name: HeadlineHunt
Version: 0.1.12
Summary: A python library for news.
License: MIT
Keywords: News
Author: mraniki
Author-email: 8766259+mraniki@users.noreply.github.com
Requires-Python: >=3.10,<4.0
Classifier: License :: OSI Approved :: MIT License
Classifier: Programming Language :: Python :: 3
Classifier: Programming Language :: Python :: 3.10
Classifier: Programming Language :: Python :: 3.11
Requires-Dist: aiohttp (>=3.8.4,<4.0.0)
Requires-Dist: alpha-vantage
Requires-Dist: beautifulsoup4 (>=4.12.2,<5.0.0)
Requires-Dist: dateparser (>=1.1.8,<2.0.0)
Requires-Dist: dynaconf (>=3.1.12,<4.0.0)
Requires-Dist: feedparser (>=6.0.10,<7.0.0)
Requires-Dist: finnhub-python
Requires-Dist: loguru (==0.6.0)
Requires-Dist: news-please
Requires-Dist: newsapi-python
Requires-Dist: prettytable (>=3.8.0,<4.0.0)
Requires-Dist: requests (>=2.31.0,<3.0.0)
Requires-Dist: xmltodict
Project-URL: Changelog, https://github.com/mraniki/headlinehunt/blob/dev/CHANGELOG.rst
Project-URL: Issues, https://github.com/mraniki/headlinehunt/issues
Project-URL: Support, https://github.com/mraniki/headlinehunt/discussions
